MANIFEST.in
README.md
README.txt
html5witch.py
setup.py
html5witch.egg-info/PKG-INFO
html5witch.egg-info/SOURCES.txt
html5witch.egg-info/dependency_links.txt
html5witch.egg-info/requires.txt
html5witch.egg-info/top_level.txt
tests/html5witch_tests.py
tests/expected/link_elements.html
tests/expected/script_elements.html
tests/expected/simple_document.html