Metadata-Version: 1.0
Name: html5witch
Version: 0.2.1
Summary: html5witch offers Pythonic HTML5 generation based on xmlwitch
Home-page: http://jonasgalvez.com.br/Software/HTML5Witch.html
Author: Jonas Galvez
Author-email: jonasgalvez@gmail.com
License: BSD
Platform: Python 2.5 and later
Classifier: Intended Audience :: Developers
Classifier: Development Status :: 4 - Beta
Classifier: License :: OSI Approved :: BSD License
Classifier: Operating System :: OS Independent
Classifier: Programming Language :: Python
Classifier: Topic :: Software Development :: Libraries
Classifier: Topic :: Text Processing :: Markup :: HTML
